ukw_ml_tools/__init__.py
ukw_ml_tools/fieldnames.py
ukw_ml_tools/_depreceated/__init__.py
ukw_ml_tools/_depreceated/__main__.py
ukw_ml_tools/_depreceated/cli.py
ukw_ml_tools/_depreceated/depreciated.py
ukw_ml_tools/_depreceated/classes/__init__.py
ukw_ml_tools/_depreceated/classes/ai_predictor.py
ukw_ml_tools/_depreceated/classes/ai_trainer.py
ukw_ml_tools/_depreceated/classes/db.py
ukw_ml_tools/_depreceated/classes/db_extern.py
ukw_ml_tools/_depreceated/classes/db_images.py
ukw_ml_tools/_depreceated/classes/db_interventions.py
ukw_ml_tools/_depreceated/classes/db_tests.py
ukw_ml_tools/_depreceated/classes/fastcat_annotation.py
ukw_ml_tools/_depreceated/classes/fieldnames.py
ukw_ml_tools/_depreceated/classes/image.py
ukw_ml_tools/_depreceated/classes/intervention.py
ukw_ml_tools/_depreceated/classes/labelstudio.py
ukw_ml_tools/_depreceated/classes/streamlit_generator.py
ukw_ml_tools/_depreceated/classes/terminology.py
ukw_ml_tools/_depreceated/classes/test_data_intervention.py
ukw_ml_tools/_depreceated/classes/utils.py
ukw_ml_tools/_depreceated/datamodules/__init__.py
ukw_ml_tools/_depreceated/datamodules/binary_image_classification_dm.py
ukw_ml_tools/_depreceated/datasets/__init__.py
ukw_ml_tools/_depreceated/datasets/binary_image_classification_ds.py
ukw_ml_tools/_depreceated/datasets/utils.py
ukw_ml_tools/_depreceated/db/__init__.py
ukw_ml_tools/_depreceated/db/conversions.py
ukw_ml_tools/_depreceated/db/crud.py
ukw_ml_tools/_depreceated/db/db_import.py
ukw_ml_tools/_depreceated/db/validation.py
"ukw_ml_tools/_depreceated/ls/__init__,py"
ukw_ml_tools/_depreceated/ls/utils.py
ukw_ml_tools/_depreceated/models/__init__.py
ukw_ml_tools/_depreceated/models/pl_googlenet.py
ukw_ml_tools/_depreceated/models/pl_ileum_detection_resnet.py
ukw_ml_tools/_depreceated/models/pl_polyp_detection_resnet.py
ukw_ml_tools/_depreceated/models/utils.py
ukw_ml_tools/_depreceated/prelabeling/__init__.py
ukw_ml_tools/_depreceated/prelabeling/binary_predictions.py
ukw_ml_tools-0.3.0.dist-info/AUTHORS.rst
ukw_ml_tools-0.3.0.dist-info/LICENSE
ukw_ml_tools-0.3.0.dist-info/METADATA
ukw_ml_tools-0.3.0.dist-info/WHEEL
ukw_ml_tools-0.3.0.dist-info/entry_points.txt
ukw_ml_tools-0.3.0.dist-info/top_level.txt
ukw_ml_tools-0.3.0.dist-info/RECORD
